evescript/README.md
evescript/__init__.py
evescript/compiler.py
evescript/decompiler.py
evescript/exceptions.py
evescript/executor.py
evescript/eveparser/.gitignore
evescript/eveparser/EveScript.g4
evescript/eveparser/Makefile
evescript/eveparser/__init__.py
evescript/eveparser/parser_output/EveScript.interp
evescript/eveparser/parser_output/EveScript.tokens
evescript/eveparser/parser_output/EveScriptLexer.interp
evescript/eveparser/parser_output/EveScriptLexer.py
evescript/eveparser/parser_output/EveScriptLexer.tokens
evescript/eveparser/parser_output/EveScriptParser.py
evescript/eveparser/parser_output/__init__.py
evescript-0.5.0.dist-info/AUTHORS.rst
evescript-0.5.0.dist-info/LICENSE
evescript-0.5.0.dist-info/METADATA
evescript-0.5.0.dist-info/WHEEL
evescript-0.5.0.dist-info/top_level.txt
evescript-0.5.0.dist-info/RECORD
