Metadata-Version: 2.1
Name: evescript
Version: 0.5.0
Summary: A simple script language for event-based automation tasks.
Home-page: https://github.com/charlee/evescript
Author: Charlee Li
Author-email: oda.charlee@gmail.com
License: MIT
Project-URL: Documentation, https://evescript.readthedocs.io/
Project-URL: Changelog, https://evescript.readthedocs.io/en/latest/changelog.html
Project-URL: Issue Tracker, https://github.com/charlee/evescript/issues
Keywords: script,evescript,automation
Platform: UNKNOWN
Classifier: Development Status :: 5 - Production/Stable
Classifier: Intended Audience :: Developers
Classifier: License :: OSI Approved :: MIT License
Classifier: Operating System :: Unix
Classifier: Operating System :: POSIX
Classifier: Operating System :: Microsoft :: Windows
Classifier: Programming Language :: Python
Classifier: Programming Language :: Python :: 3
Classifier: Programming Language :: Python :: 3 :: Only
Classifier: Programming Language :: Python :: 3.6
Classifier: Programming Language :: Python :: 3.7
Classifier: Programming Language :: Python :: 3.8
Classifier: Programming Language :: Python :: 3.9
Classifier: Programming Language :: Python :: Implementation :: CPython
Classifier: Programming Language :: Python :: Implementation :: PyPy
Classifier: Topic :: Utilities
Requires-Python: >=3.6
Requires-Dist: antlr4-python3-runtime (==4.9.2)
